setup.py
graphite_cleaner/__init__.py
graphite_cleaner/main.py
graphite_cleaner.egg-info/PKG-INFO
graphite_cleaner.egg-info/SOURCES.txt
graphite_cleaner.egg-info/dependency_links.txt
graphite_cleaner.egg-info/entry_points.txt
graphite_cleaner.egg-info/requires.txt
graphite_cleaner.egg-info/top_level.txt