Metadata-Version: 1.0
Name: graphite-cleaner
Version: 0.1.1
Summary: Graphite Whisper stale database files remover
Home-page: https://github.com/operasoftware/graphite-cleaner
Author: Services Wroclaw Team
Author-email: svc-code@opera.com
License: UNKNOWN
Platform: UNKNOWN
